arjun/__init__.py
arjun/__main__.py
arjun/core/__init__.py
arjun/core/anomaly.py
arjun/core/bruter.py
arjun/core/colors.py
arjun/core/config.py
arjun/core/engine.py
arjun/core/error_handler.py
arjun/core/exporter.py
arjun/core/importer.py
arjun/core/logger.py
arjun/core/prompt.py
arjun/core/requester.py
arjun/core/scanner.py
arjun/core/utils.py
arjun/plugins/__init__.py
arjun/plugins/commoncrawl.py
arjun/plugins/heuristic.py
arjun/plugins/otx.py
arjun/plugins/wayback.py
arjun/plugins/wl.py
arjun_cli-0.1.0.dist-info/licenses/LICENSE
arjun_cli-0.1.0.dist-info/METADATA
arjun_cli-0.1.0.dist-info/WHEEL
arjun_cli-0.1.0.dist-info/entry_points.txt
arjun_cli-0.1.0.dist-info/top_level.txt
arjun_cli-0.1.0.dist-info/RECORD
