Metadata-Version: 2.4
Name: arjun-cli
Version: 0.1.0
Summary: HTTP Parameter Discovery Suite
Author-email: BugHunter <mywebservices.preorder540@passinbox.com>
License: Copyright (c) 2026
Project-URL: Homepage, https://github.com/s0md3v/Arjun
Project-URL: Bug Tracker, https://github.com/s0md3v/Arjun/issues
Requires-Python: >=3.8
License-File: LICENSE
Requires-Dist: requests>=2.0.0
Requires-Dist: dicttoxml>=1.7.4
Requires-Dist: cloudscraper>=1.2.70
Requires-Dist: fake-useragent>=1.1.0
Requires-Dist: ratelimit>=2.2.1
Dynamic: license-file
